LICENSE
MANIFEST.in
README.rst
requirements-dev.txt
requirements.txt
setup.py
senior_hcm/__init__.py
senior_hcm.egg-info/PKG-INFO
senior_hcm.egg-info/SOURCES.txt
senior_hcm.egg-info/dependency_links.txt
senior_hcm.egg-info/not-zip-safe
senior_hcm.egg-info/requires.txt
senior_hcm.egg-info/top_level.txt