Metadata-Version: 1.1
Name: senior-hcm
Version: 0.0.2
Summary: Client to access Senior HCM
Home-page: https://github.com/Lrcezimbra/senior-hcm
Author: Lucas Rangel Cezimbra
Author-email: lucas.cezimbra@gmail.com
License: LGPLv2
Keywords: senior,hcm,requests,payroll
Platform: UNKNOWN
Classifier: Development Status :: 4 - Beta
Classifier: Intended Audience :: Developers
Classifier: License :: OSI Approved :: GNU Lesser General Public License v2 (LGPLv2)
Classifier: Programming Language :: Python :: 3
Classifier: Programming Language :: Python :: 3.6
Classifier: Programming Language :: Python :: 3.7
Classifier: Programming Language :: Python :: 3 :: Only
